laptrack/__init__.py
laptrack/__main__.py
laptrack/_coo_matrix_builder.py
laptrack/_cost_matrix.py
laptrack/_optimization.py
laptrack/_overlap_tracking.py
laptrack/_tracking.py
laptrack/_typing_utils.py
laptrack/data_conversion.py
laptrack/datasets.py
laptrack/metric_utils.py
laptrack/py.typed
laptrack/scores.py
laptrack/utils.py
laptrack-0.16.2.dist-info/LICENSE.rst
laptrack-0.16.2.dist-info/METADATA
laptrack-0.16.2.dist-info/WHEEL
laptrack-0.16.2.dist-info/entry_points.txt
laptrack-0.16.2.dist-info/RECORD
