Metadata-Version: 2.1
Name: laptrack
Version: 0.16.2
Summary: LapTrack
Home-page: https://github.com/yfukai/laptrack
License: BSD-3-Clause
Author: Yohsuke Fukai
Author-email: ysk@yfukai.net
Requires-Python: >=3.8,<3.13
Classifier: Development Status :: 4 - Beta
Classifier: Intended Audience :: Developers
Classifier: Intended Audience :: Science/Research
Classifier: License :: OSI Approved :: BSD License
Classifier: Natural Language :: English
Classifier: Programming Language :: Python :: 3
Classifier: Programming Language :: Python :: 3.8
Classifier: Programming Language :: Python :: 3.9
Classifier: Programming Language :: Python :: 3.10
Classifier: Programming Language :: Python :: 3.11
Classifier: Programming Language :: Python :: 3.12
Requires-Dist: click (>=8.0.1,<9.0.0)
Requires-Dist: networkx (>=2.6.1,<3.0.0)
Requires-Dist: numpy (>=1.24,<2.0) ; python_version < "3.9"
Requires-Dist: numpy (>=1.26,<2.0) ; python_version >= "3.9"
Requires-Dist: pandas (>=1.3.1,<2.0.0)
Requires-Dist: pooch (>=1.6.0,<2.0.0)
Requires-Dist: pydantic (>=1.10.2,<2.0.0)
Requires-Dist: scikit-image (>=0.19.3,<0.20.0) ; python_version < "3.11"
Requires-Dist: scikit-image (>=0.20.0,<1.0.0) ; python_version >= "3.11"
Requires-Dist: scikit-learn (>=1.3.1,<2.0.0)
Requires-Dist: scipy (>=1.12.0,<2.0.0) ; python_version >= "3.12"
Requires-Dist: scipy (>=1.8.0,<2.0.0) ; python_version < "3.12"
Requires-Dist: typing-extensions (>=4.1.0,<5.0.0)
Project-URL: Changelog, https://github.com/yfukai/laptrack/releases
Project-URL: Documentation, https://laptrack.readthedocs.io
Project-URL: Repository, https://github.com/yfukai/laptrack
